nosebook.py
nosebook-0.4.0.dist-info/WHEEL
nosebook-0.4.0.dist-info/DESCRIPTION.rst
nosebook-0.4.0.dist-info/metadata.json
nosebook-0.4.0.dist-info/RECORD
nosebook-0.4.0.dist-info/METADATA
nosebook-0.4.0.dist-info/entry_points.txt
nosebook-0.4.0.dist-info/top_level.txt
