Metadata-Version: 2.0
Name: nosebook
Version: 0.4.0
Summary: a nose plugin for IPython notebooks
Home-page: http://github.com/bollwyvl/nosebook
Author: Nicholas Bollweg
Author-email: nick.bollweg@gmail.com
License: BSD
Keywords: IPython nose
Platform: UNKNOWN
Classifier: Topic :: Utilities
Classifier: Framework :: IPython
Classifier: Natural Language :: English
Classifier: Programming Language :: Python
Classifier: Intended Audience :: Developers
Classifier: Development Status :: 3 - Alpha
Classifier: Operating System :: OS Independent
Classifier: Programming Language :: Python :: 3
Classifier: Programming Language :: Python :: 2
Classifier: License :: OSI Approved :: BSD License
Classifier: Topic :: Software Development :: Testing
